scrapy_rabbitmq_scheduler_saylor/__init__.py
scrapy_rabbitmq_scheduler_saylor/connection.py
scrapy_rabbitmq_scheduler_saylor/middleware.py
scrapy_rabbitmq_scheduler_saylor/picklecompat.py
scrapy_rabbitmq_scheduler_saylor/pipelines.py
scrapy_rabbitmq_scheduler_saylor/queue.py
scrapy_rabbitmq_scheduler_saylor/scheduler.py
scrapy_rabbitmq_scheduler_saylor/spiders.py
scrapy_rabbitmq_scheduler_saylor-1.0.3.dist-info/METADATA
scrapy_rabbitmq_scheduler_saylor-1.0.3.dist-info/WHEEL
scrapy_rabbitmq_scheduler_saylor-1.0.3.dist-info/top_level.txt
scrapy_rabbitmq_scheduler_saylor-1.0.3.dist-info/RECORD
